pycellsquid/__init__.py
pycellsquid-0.0.1.dist-info/METADATA
pycellsquid-0.0.1.dist-info/WHEEL
pycellsquid-0.0.1.dist-info/top_level.txt
pycellsquid-0.0.1.dist-info/RECORD
