Metadata-Version: 2.1
Name: pycellsquid
Version: 0.0.1
Summary: Use Excel functions with python!
Home-page: UNKNOWN
Author: Siddharth Sonnad
Author-email: <sonnadsiddharth@gmail.com>
License: UNKNOWN
Keywords: python,excel,functions,function
Platform: UNKNOWN
Classifier: Development Status :: 1 - Planning
Classifier: Intended Audience :: Developers
Classifier: Programming Language :: Python :: 3
Classifier: Operating System :: Unix
Classifier: Operating System :: MacOS :: MacOS X
Classifier: Operating System :: Microsoft :: Windows
